anicham/__init__.py
anicham/compiler.py
anicham/parser/__init__.py
anicham/parser/grammar/TamizhLexer.py
anicham/parser/grammar/TamizhListener.py
anicham/parser/grammar/TamizhParser.py
anicham/parser/grammar/TamizhVisitor.py
anicham/parser/grammar/__init__.py
anicham/parser/grammar/Yappu/VenbaLexer.py
anicham/parser/grammar/Yappu/VenbaListener.py
anicham/parser/grammar/Yappu/VenbaParser.py
anicham/parser/grammar/Yappu/VenbaVisitor.py
anicham/parser/grammar/Yappu/__init__.py
anicham/visitors/__init__.py
anicham/visitors/tamizh_visitor_impl.py
anicham/visitors/venba_visitor_impl.py
anicham/visitors/ast/__init__.py
anicham/visitors/ast/venba.py
anicham-0.0.6.dist-info/LICENSE
anicham-0.0.6.dist-info/METADATA
anicham-0.0.6.dist-info/WHEEL
anicham-0.0.6.dist-info/top_level.txt
anicham-0.0.6.dist-info/RECORD
