Metadata-Version: 2.1
Name: anicham
Version: 0.0.6
Summary: Tamizh language parser, grammatical tools, utils, and more
Author-email: Amuthan Mannan <amuthanmannar4@gmail.com>
Project-URL: Homepage, https://github.com/MannarAmuthan/anicham.py
Project-URL: Issues, https://github.com/MannarAmuthan/anicham.py/issues
Classifier: Programming Language :: Python :: 3
Classifier: License :: OSI Approved :: MIT License
Classifier: Operating System :: OS Independent
Requires-Python: >=3
License-File: LICENSE
Requires-Dist: antlr4-python3-runtime >=4
Requires-Dist: antlr4-tools >=0.2.1
